dydx/__init__.py
dydx/client.py
dydx/util.py
tests/__init__.py
tests/test_client.py
dydx-0.0.4.dist-info/LICENSE
dydx-0.0.4.dist-info/METADATA
dydx-0.0.4.dist-info/WHEEL
dydx-0.0.4.dist-info/top_level.txt
dydx-0.0.4.dist-info/RECORD
